realtime_twitter_api/__init__.py
realtime_twitter_api-0.2.dist-info/METADATA
realtime_twitter_api-0.2.dist-info/WHEEL
realtime_twitter_api-0.2.dist-info/top_level.txt
realtime_twitter_api-0.2.dist-info/RECORD
