Metadata-Version: 2.1
Name: realtime-twitter-api
Version: 0.2
Requires-Dist: requests
